{
    "KDHartreeFock": {
        "V1_0": 63.2761,
        "V1_asymm": 22.7757,
        "V1_A": 0.00869099,
        "V2_0_n": 0.00837227,
        "V2_A_n": 9.2939e-06,
        "V3_0_n": 3.25285e-05,
        "V3_A_n": 7.87426e-08,
        "V2_0_p": 0.00407146,
        "V2_A_p": 2.52826e-05,
        "V3_0_p": 1.37765e-05,
        "V3_A_p": 1.0011e-07,
        "V4_0": 2.8005e-08,
        "r_0": 1.28842,
        "r_A": 0.589703,
        "a_0": 0.750581,
        "a_A": 0.00109211
    },
    "KDCoulomb": {
        "r_C_0": 1.11973,
        "r_C_A": 2.62311,
        "r_C_A2": 33.0509
    },
    "KDRealSpinOrbit": {
        "V1_0": 9.17886,
        "V1_A": -0.00492986,
        "V2_0": 0.0269769,
        "r_0": 1.03501,
        "r_A": -0.251981,
        "a_0": 0.580182
    },
    "KDImagSpinOrbit": {
        "W1_0": -6.71422,
        "W2_0": 299.494
    },
    "KDImagVolume": {
        "W1_0_n": 20.2222,
        "W1_A_n": 0.0368334,
        "W1_0_p": 13.5856,
        "W1_A_p": 0.0852668,
        "W2_0": 148.429,
        "W2_A": 0.355647
    },
    "KDImagSurface": {
        "D1_0": 13.9978,
        "D1_asymm": 28.902,
        "D2_0": -0.0161158,
        "D2_A": 0.0305629,
        "D2_A2": 9.50094,
        "D2_A3": 215.215,
        "D3_0": 11.2826,
        "r_0": 1.27344,
        "r_A": 0.0437952,
        "a_0_n": 0.562263,
        "a_A_n": -0.00247984,
        "a_0_p": 0.542661,
        "a_A_p": 0.0017154
    }
}