{
    "KDHartreeFock": {
        "V1_0": 58.8421,
        "V1_asymm": 3.64217,
        "V1_A": 0.0347207,
        "V2_0_n": 0.00415496,
        "V2_A_n": -1.38725e-05,
        "V3_0_n": -6.39969e-06,
        "V3_A_n": -6.07585e-08,
        "V2_0_p": 0.00568941,
        "V2_A_p": 1.66703e-05,
        "V3_0_p": 1.18015e-06,
        "V3_A_p": 1.31272e-07,
        "V4_0": -3.37222e-08,
        "r_0": 1.28126,
        "r_A": 0.41236,
        "a_0": 0.666322,
        "a_A": -0.00034575
    },
    "KDCoulomb": {
        "r_C_0": 1.26333,
        "r_C_A": 0.16071,
        "r_C_A2": 14.1875
    },
    "KDRealSpinOrbit": {
        "V1_0": 5.49753,
        "V1_A": 0.0160712,
        "V2_0": 0.00825676,
        "r_0": 1.07899,
        "r_A": 0.147839,
        "a_0": 0.531795
    },
    "KDImagSpinOrbit": {
        "W1_0": -3.66832,
        "W2_0": 213.781
    },
    "KDImagVolume": {
        "W1_0_n": 22.1303,
        "W1_A_n": -0.0166931,
        "W1_0_p": 20.1554,
        "W1_A_p": -0.0128692,
        "W2_0": 84.6999,
        "W2_A": -0.132856
    },
    "KDImagSurface": {
        "D1_0": 17.9669,
        "D1_asymm": 7.53753,
        "D2_0": 0.0510116,
        "D2_A": -0.0143127,
        "D2_A2": 3.54013,
        "D2_A3": 276.309,
        "D3_0": 15.7402,
        "r_0": 1.36208,
        "r_A": 0.0287198,
        "a_0_n": 0.623016,
        "a_A_n": -0.000297794,
        "a_0_p": 0.554359,
        "a_A_p": 0.00189874
    }
}